{
  "date": "2026-07-23",
  "run_count": 3,
  "notes": {
    "seguridad": [
      {
        "title": "Exfiscal vinculado a proceso por huachicol y crimen organizado",
        "summary": "Ernesto Ruffo y siete coimputados fueron vinculados a proceso por delitos de huachicol fiscal y delincuencia organizada.",
        "source": "ZETA Tijuana",
        "url": "https://zetatijuana.com/2026/07/ernesto-ruffo-y-siete-coimputados-fueron-vinculados-a-proceso-por-huachicol-fiscal-y-delincuencia-organizada/",
        "_added_at": "2026-07-23T07:24:16.473449-07:00"
      },
      {
        "title": "Identifican restos de desaparecido en 2023 en Miguel Alemán",
        "summary": "Restos humanos hallados en Miguel Alemán fueron identificados como Juan Antonio, desaparecido hace tres años.",
        "source": "ZETA Tijuana",
        "url": "https://zetatijuana.com/2026/07/restos-humanos-localizados-en-miguel-aleman-pertenecen-a-juan-antonio-desaparecido-en-2023/",
        "_added_at": "2026-07-23T07:24:16.473449-07:00"
      },
      {
        "title": "Cuatro detenidos por extorsión; uno era agente estatal",
        "summary": "Autoridades capturan a cuatro personas acusadas de extorsión en Tijuana, uno de ellos agente de Ensenada.",
        "source": "ZETA Tijuana",
        "url": "https://zetatijuana.com/2026/07/cuatro-detenidos-por-extorsion-en-tijuana-uno-es-agente-de-ensenada/",
        "_added_at": "2026-07-23T01:42:02.661285-07:00"
      },
      {
        "title": "Sicario del CJNG capturado en Tecate",
        "summary": "Fuerzas de seguridad detienen a \"El Vampi\", presunto sicario de Cartel Jalisco Nueva Generación.",
        "source": "ZETA Tijuana",
        "url": "https://zetatijuana.com/2026/07/en-tecate-cae-el-vampi-sicario-del-cjng/",
        "_added_at": "2026-07-23T01:42:02.661285-07:00"
      },
      {
        "title": "Restos de desaparecido en 2023 identificados en Tijuana",
        "summary": "Hallazgo de restos humanos en Miguel Alemán corresponden a Juan Antonio Leal, desaparecido hace tres años.",
        "source": "AFN Tijuana",
        "url": "https://www.afntijuana.info/seguridad/179458_celula_de_busqueda_localiza_restos_de_juan_antonio_leal_desaparecido_en_2023",
        "_added_at": "2026-07-23T01:42:02.661285-07:00"
      },
      {
        "title": "Cuerpo calcinado localizado en vehículo en La Morita",
        "summary": "Encuentran cadáver carbonizado dentro de auto quemado en zona de Tijuana.",
        "source": "El Mexicano",
        "url": "https://el-mexicano.com.mx/Noticia/Policiaca/97105/Localizan-cuerpo-calcinado-dentro-de-un-veh%C3%ADculo-en-La-Morita",
        "_added_at": "2026-07-23T01:42:02.661285-07:00"
      }
    ],
    "politica": [
      {
        "title": "Diputado denuncia aplicación selectiva de la ley",
        "summary": "Legislador exhibe en tribuna la falta de equidad en la aplicación de normas legales en la entidad.",
        "source": "AFN Tijuana",
        "url": "https://www.afntijuana.info/nacionales/179469_denuncia_max_garcia_la_aplicacion_selectiva_de_la_ley_exhibe_cartel_en_tribuna",
        "_added_at": "2026-07-23T04:17:26.060809-07:00"
      },
      {
        "title": "Alcalde exige revisión de juez que frenó captura de Ruffo",
        "summary": "Autoridad municipal demanda al Tribunal de Disciplina investigar a magistrado por obstaculizar proceso contra Ruffo.",
        "source": "ZETA Tijuana",
        "url": "https://zetatijuana.com/2026/07/alcalde-exige-al-tribunal-de-disciplina-revisar-a-juez-que-freno-captura-de-ruffo/",
        "_added_at": "2026-07-23T01:42:02.661285-07:00"
      },
      {
        "title": "Hija de Ruffo pide protección a embajada estadounidense",
        "summary": "Familia de Ruffo solicita asilo en EU argumentando persecución por cargos de huachicol fiscal.",
        "source": "AFN Tijuana",
        "url": "https://www.afntijuana.info/informacion_general/179471_hija_de_ruffo_pide_proteccion_a_la_embajada_de_eu_en_mexico",
        "_added_at": "2026-07-23T01:42:02.661285-07:00"
      },
      {
        "title": "Inquieta posible alianza entre Movimiento Ciudadano y PT",
        "summary": "Analistas expresan preocupación sobre potencial coalición política entre ambas fuerzas electorales.",
        "source": "AFN Tijuana",
        "url": "https://www.afntijuana.info/afn_politico/179465_inquieta_una_eventual_alianza_entre_mc_y_el_partido_del_trabajo",
        "_added_at": "2026-07-23T01:42:02.661285-07:00"
      }
    ],
    "economia": [
      {
        "title": "Exportaciones de maquiladoras caen 9.6% en Baja California",
        "summary": "Las exportaciones del sector maquila registraron una caída de casi 10% en período reciente.",
        "source": "AFN Tijuana",
        "url": "https://www.afntijuana.info/empresarial/179473_caen_9_6_las_exportaciones_de_maquiladoras_en_bc",
        "_added_at": "2026-07-23T07:24:16.473449-07:00"
      },
      {
        "title": "Inflación en BC alcanza 2.13% en primera quincena de julio",
        "summary": "Índice inflacionario en Baja California se ubicó en 2.13% durante la primera mitad del mes.",
        "source": "AFN Tijuana",
        "url": "https://www.afntijuana.info/empresarial/179472_inflacion_de_bc_llega_a_2_13_en_la_primera_quincena_de_julio",
        "_added_at": "2026-07-23T07:24:16.473449-07:00"
      },
      {
        "title": "Toyota aclaración sobre retirada gradual de México",
        "summary": "Automotriz aclara que salida de operaciones hacia EU será progresiva, no inmediata como Trump anunció.",
        "source": "ZETA Tijuana",
        "url": "https://zetatijuana.com/2026/07/trump-celebra-salida-de-toyota-de-mexico-rumbo-a-eu-automotriz-aclara-que-sera-gradual/",
        "_added_at": "2026-07-23T01:42:02.661285-07:00"
      },
      {
        "title": "Valle de Guadalupe muestra recuperación económica",
        "summary": "Cámara de Comercio reporta mejoría financiera en la región vinícola durante presente año.",
        "source": "AFN Tijuana",
        "url": "https://www.afntijuana.info/informacion_general/179464_valle_de_guadalupe_registra_recuperacion_economica_este_ano_cce_tijuana",
        "_added_at": "2026-07-23T01:42:02.661285-07:00"
      }
    ],
    "sociedad": [
      {
        "title": "Sacerdote condenado por violación agravada",
        "summary": "Tribunales condenan a clérigo acusado de delito sexual agravado contra menor.",
        "source": "ZETA Tijuana",
        "url": "https://zetatijuana.com/2026/07/condenan-a-sacerdote-acusado-de-violacion-impropia-agravada/",
        "_added_at": "2026-07-23T04:17:26.060809-07:00"
      },
      {
        "title": "Retiran apoyo a viudas de policías tras desacuerdo",
        "summary": "Sindicatura anuncia suspensión de asistencia provisional a viudas de elementos caídos por malinterpretaciones.",
        "source": "AFN Tijuana",
        "url": "https://www.afntijuana.info/informacion_general/179463_anuncian_retiro_de_apoyo_provisional_a_viudas_de_policias_para_evitar_malinterpretaciones",
        "_added_at": "2026-07-23T04:17:26.060809-07:00"
      },
      {
        "title": "Retiran apoyo provisional a viudas de policías",
        "summary": "Autoridades suspenden ayuda a viudas de elementos caídos tras conflicto con manifestantes.",
        "source": "ZETA Tijuana",
        "url": "https://zetatijuana.com/2026/07/retiraran-apoyo-a-viudas-de-policias-tras-desacuerdo-entre-sindicatura-y-manifestantes/",
        "_added_at": "2026-07-23T01:42:02.661285-07:00"
      },
      {
        "title": "Treinta familias participan en proceso de adopción DIF",
        "summary": "Instituto estatal promueve adopciones con participación significativa de familias interesadas.",
        "source": "AFN Tijuana",
        "url": "https://www.afntijuana.info/informacion_general/179467_al_menos_30_familias_participan_en_proceso_de_adopcion_de_ninos_del_dif_estatal",
        "_added_at": "2026-07-23T01:42:02.661285-07:00"
      },
      {
        "title": "Servicio de agua al 90% durante altas temperaturas",
        "summary": "Autoridades restablecen suministro de agua en Tijuana ante crisis por calor extremo.",
        "source": "El Mexicano",
        "url": "https://el-mexicano.com.mx/Noticia/Tijuana/97094/Se-establece-el-servicio-del-agua-al-90%25-en-Tijuana-derivado-de-las-altas-temperaturas",
        "_added_at": "2026-07-23T01:42:02.661285-07:00"
      }
    ]
  },
  "last_updated": "2026-07-23T07:24:16.473449-07:00"
}